mrbcl/__init__.py
mrbcl/command.py
mrbcl/config.py
mrbcl/logging.py
mrbcl/config/config.yml
mrbcl/config/log.yml
mrbcl/database/__init__.py
mrbcl/database/db.py
mrbcl/database/dmdb.py
mrbcl/dingtalk/__init__.py
mrbcl/dingtalk/dingtalkrobot.py
mrbcl/hooks/__init__.py
mrbcl/hooks/hook-dmPython.py
mrbcl/utils/__init__.py
mrbcl/utils/common.py
mrbcl/utils/compressutil.py
mrbcl/utils/encipher.py
mrbcl/utils/fileutil.py
mrbcl/utils/md5util.py
mrbcl-1.0.3.5.dist-info/METADATA
mrbcl-1.0.3.5.dist-info/WHEEL
mrbcl-1.0.3.5.dist-info/top_level.txt
mrbcl-1.0.3.5.dist-info/RECORD
